arraytex/__init__.py
arraytex/__main__.py
arraytex/api.py
arraytex/errors.py
arraytex/py.typed
arraytex/utils.py
arraytex-0.0.9.dist-info/LICENSE
arraytex-0.0.9.dist-info/METADATA
arraytex-0.0.9.dist-info/WHEEL
arraytex-0.0.9.dist-info/entry_points.txt
arraytex-0.0.9.dist-info/RECORD
