Metadata-Version: 2.1
Name: arraytex
Version: 0.0.9
Summary: ArrayTeX
Home-page: https://github.com/dbatten5/arraytex
License: MIT
Author: Dom Batten
Author-email: dominic.batten@googlemail.com
Requires-Python: >=3.8,<4.0
Classifier: Development Status :: 3 - Alpha
Classifier: License :: OSI Approved :: MIT License
Classifier: Programming Language :: Python :: 3
Classifier: Programming Language :: Python :: 3.8
Classifier: Programming Language :: Python :: 3.9
Classifier: Programming Language :: Python :: 3.10
Classifier: Programming Language :: Python :: 3.11
Requires-Dist: click (>=8.0.1)
Requires-Dist: numpy (>=1.24.2,<2.0.0)
Requires-Dist: pyperclip (>=1.8.2,<2.0.0)
Requires-Dist: typing-extensions (>=4.5.0,<5.0.0)
Project-URL: Changelog, https://github.com/dbatten5/arraytex/releases
Project-URL: Documentation, https://arraytex.readthedocs.io
Project-URL: Repository, https://github.com/dbatten5/arraytex
